pyshell/__init__.py
pyshell/pyshell.py
pyshell_bash-0.1.0a2.dist-info/LICENSE.txt
pyshell_bash-0.1.0a2.dist-info/METADATA
pyshell_bash-0.1.0a2.dist-info/WHEEL
pyshell_bash-0.1.0a2.dist-info/entry_points.txt
pyshell_bash-0.1.0a2.dist-info/top_level.txt
pyshell_bash-0.1.0a2.dist-info/RECORD
