Metadata-Version: 2.2
Name: pyshell-bash
Version: 0.1.0a2
Summary: An interactive bash/sh shell in Python
Author: SteveGaming62
Author-email: anon@dev.com
Classifier: Programming Language :: Python :: 3
Classifier: License :: OSI Approved :: MIT License
Classifier: Operating System :: OS Independent
Requires-Python: >=3.6
License-File: LICENSE.txt
Dynamic: author
Dynamic: author-email
Dynamic: classifier
Dynamic: description
Dynamic: description-content-type
Dynamic: requires-python
Dynamic: summary
